nuclear_helper/__init__.py
nuclear_helper/alpha_particle_generation.py
nuclear_helper/const_oxygen.py
nuclear_helper/get_parametrization_for_integrated_deVries.py
nuclear_helper/grid_oxygen.py
nuclear_helper/hostpot_number_nucleon.py
nuclear_helper/main.py
nuclear_helper/oxygen.py
nuclear_helper/plotting.py
nuclear_helper/tetrahedron_geometry.py
nuclear_helper-1.1.0.dist-info/licenses/LICENSE
nuclear_helper-1.1.0.dist-info/METADATA
nuclear_helper-1.1.0.dist-info/WHEEL
nuclear_helper-1.1.0.dist-info/top_level.txt
nuclear_helper-1.1.0.dist-info/RECORD
