Metadata-Version: 2.4
Name: nuclear_helper
Version: 1.1.0
Summary: A package to compute the hotspot structure of a tetrahedral alpha-clustered oxygen
Home-page: https://github.com/MatasMarek/nuclear_helper
Author: Marek Matas
Author-email: marek.matas@fjfi.cvut.cz
License: GNU GENERAL PUBLIC LICENSE
Classifier: Intended Audience :: Science/Research
Classifier: Programming Language :: Python :: 3
Classifier: Programming Language :: Python :: 3.4
Classifier: Programming Language :: Python :: 3.5
Classifier: Programming Language :: Python :: 3.7
Classifier: Programming Language :: Python :: 3.9
License-File: LICENSE
Requires-Dist: scipy
Requires-Dist: numpy
Requires-Dist: matplotlib
Dynamic: author
Dynamic: author-email
Dynamic: classifier
Dynamic: home-page
Dynamic: license
Dynamic: license-file
Dynamic: requires-dist
Dynamic: summary
